_splat.c
dew_drop.py
example.py
filter.c
frag.c
setup.py
signal.c
sine_table.c
source.c
spline.c
test.py
splat/__init__.py
splat/data.py
splat/filters.py
splat/gen.py
splat/interpol.py
splat/plot.py
splat/scales.py
splat/seq.py
splat/sources.py
verdigris.mu_splat.egg-info/PKG-INFO
verdigris.mu_splat.egg-info/SOURCES.txt
verdigris.mu_splat.egg-info/dependency_links.txt
verdigris.mu_splat.egg-info/top_level.txt